binchicken/__init__.py
binchicken/binchicken.py
binchicken/common.py
binchicken/pixi.lock
binchicken/pixi.toml
binchicken/config/template_coassemble.yaml
binchicken/config/template_evaluate.yaml
binchicken/workflow/coassemble.smk
binchicken/workflow/download.smk
binchicken/workflow/evaluate.smk
binchicken/workflow/env/aviary.yml
binchicken/workflow/env/coverm.yml
binchicken/workflow/env/fastp.yml
binchicken/workflow/env/general.yml
binchicken/workflow/env/kingfisher.yml
binchicken/workflow/env/prodigal.yml
binchicken/workflow/env/r.yml
binchicken/workflow/env/singlem.yml
binchicken/workflow/scripts/abundance_weighting.py
binchicken/workflow/scripts/aviary_commands.py
binchicken/workflow/scripts/cluster_graph.py
binchicken/workflow/scripts/collect_reference_bins.py
binchicken/workflow/scripts/evaluate.R
binchicken/workflow/scripts/evaluate.py
binchicken/workflow/scripts/is_interleaved.py
binchicken/workflow/scripts/no_genomes.py
binchicken/workflow/scripts/query_processing.py
binchicken/workflow/scripts/sketch_samples.py
binchicken/workflow/scripts/summarise_coassemblies.py
binchicken/workflow/scripts/target_elusive.py
binchicken/workflow/scripts/target_weighting.py
binchicken-0.13.5.dist-info/licenses/LICENSE
binchicken-0.13.5.dist-info/METADATA
binchicken-0.13.5.dist-info/WHEEL
binchicken-0.13.5.dist-info/entry_points.txt
binchicken-0.13.5.dist-info/top_level.txt
binchicken-0.13.5.dist-info/RECORD
