Metadata-Version: 2.4
Name: binchicken
Version: 0.13.5
Summary: Bin Chicken - targeted recovery of low abundance metagenome assembled genomes through intelligent coassembly
Author-email: Samuel Aroney <samuel.aroney@outlook.com>
License:                     GNU GENERAL PUBLIC LICENSE
Project-URL: Homepage, https://github.com/AroneyS/binchicken
Project-URL: Bug Tracker, https://github.com/AroneyS/binchicken/issues
Classifier: Topic :: Scientific/Engineering :: Bio-Informatics
Requires-Python: >=3.10
License-File: LICENSE
Requires-Dist: extern==0.4.1
Requires-Dist: mamba==1.4.9
Requires-Dist: networkx==3.1
Requires-Dist: pip==25.1.1
Requires-Dist: polars==1.26.0
Requires-Dist: pyarrow==12.0.1
Requires-Dist: pyOpenSSL==25.1.0
Requires-Dist: ruamel.yaml==0.18.10
Requires-Dist: snakemake==7.32.4
Requires-Dist: sourmash==4.8.14
Requires-Dist: sourmash_plugin_branchwater==0.9.13
Dynamic: license-file
